hashpoll_cli/__init__.py
hashpoll_cli/__main__.py
hashpoll_cli/helpers/create.py
hashpoll_cli/helpers/get_poll.py
hashpoll_cli/helpers/get_responses.py
hashpoll_cli/helpers/vote.py
hashpoll_cli-0.1.6.dist-info/LICENSE
hashpoll_cli-0.1.6.dist-info/WHEEL
hashpoll_cli-0.1.6.dist-info/METADATA
hashpoll_cli-0.1.6.dist-info/RECORD
