Metadata-Version: 2.1
Name: hashpoll-cli
Version: 0.1.6
Summary: A handy CLI tool for creating polls for Hashnode. Made with ❤️ by @hashpoll.
Home-page: https://github.com/Arpan-206/hashpoll-cli
License: MIT
Keywords: tools,polls,hashnode,cli,amplify
Author: Arpan Pandey
Author-email: arpan@hackersreboot.tech
Requires-Python: >=3.8,<4.0
Classifier: License :: OSI Approved :: MIT License
Classifier: Programming Language :: Python :: 3
Classifier: Programming Language :: Python :: 3.10
Classifier: Programming Language :: Python :: 3.8
Classifier: Programming Language :: Python :: 3.9
Requires-Dist: requests (>=2.28.1,<3.0.0)
Requires-Dist: rich (>=12.5.1,<13.0.0)
Requires-Dist: typer[all] (>=0.6.1,<0.7.0)
Project-URL: Repository, https://github.com/Arpan-206/hashpoll-cli
